hak_gal/__init__.py
hak_gal/core/__init__.py
hak_gal/core/config.py
hak_gal/core/engine.py
hak_gal/core/exceptions.py
hak_gal/core/redis_session_manager.py
hak_gal/core/session_manager.py
hak_gal/layers/__init__.py
hak_gal/layers/inbound/__init__.py
hak_gal/layers/inbound/normalization_layer.py
hak_gal/layers/inbound/regex_gate.py
hak_gal/layers/inbound/sanitizer.py
hak_gal/layers/inbound/vector_guard.py
hak_gal/layers/outbound/__init__.py
hak_gal/layers/outbound/tool_guard.py
hak_gal/utils/__init__.py
hak_gal/utils/crypto.py
hak_gal/utils/json_parser.py
hak_gal/utils/secure_logger.py
hak_gal/utils/tenant_log_redactor.py
hak_gal/utils/tenant_rate_limiter.py
hak_gal/utils/tenant_redis_pool.py
layer15/__init__.py
layer15/age_router.py
layer15/crisis.py
layer15/deceptive_empathy.py
layer15/guard.py
layer15/owasp_sinks.py
layer15/rsi_childsafe.py
layer15/validators/__init__.py
layer15/validators/age_stratified_nli.py
llm_firewall/__init__.py
llm_firewall/cli.py
llm_firewall/config.py
llm_firewall/core.py
llm_firewall/guard.py
llm_firewall/policy_config.py
llm_firewall/storage.py
llm_firewall/adapters/__init__.py
llm_firewall/adapters/write_log_adapter.py
llm_firewall/adapters/auth/__init__.py
llm_firewall/adapters/auth/spatial_captcha_adapter.py
llm_firewall/agents/__init__.py
llm_firewall/agents/config.py
llm_firewall/agents/countmin_sketch.py
llm_firewall/agents/detector.py
llm_firewall/agents/example_usage.py
llm_firewall/agents/inspector.py
llm_firewall/agents/memory.py
llm_firewall/agents/state.py
llm_firewall/aggregate/__init__.py
llm_firewall/aggregate/conformal_stacker.py
llm_firewall/app/composition_root.py
llm_firewall/cache/__init__.py
llm_firewall/cache/cache_adapter.py
llm_firewall/cache/decision_cache.py
llm_firewall/cache/langcache_adapter.py
llm_firewall/calibration/__init__.py
llm_firewall/calibration/conformal_online.py
llm_firewall/calibration/lodo.py
llm_firewall/calibration/qhat_cache.py
llm_firewall/calibration/safe_bandit.py
llm_security_firewall-2.5.0.dist-info/licenses/LICENSE
llm_security_firewall-2.5.0.dist-info/METADATA
llm_security_firewall-2.5.0.dist-info/WHEEL
llm_security_firewall-2.5.0.dist-info/entry_points.txt
llm_security_firewall-2.5.0.dist-info/top_level.txt
llm_security_firewall-2.5.0.dist-info/RECORD
