Metadata-Version: 2.4
Name: llm-security-firewall
Version: 2.5.0
Summary: Cognitive Security Middleware - The 'Electronic Stability Program' (ESP) for Large Language Models. Bidirectional containment system with defense-in-depth architecture (6 validation layers), stateful tracking, and mathematical safety constraints. Validated against Unicode/encoding attacks, pattern evasion, multilingual/polyglot attacks (12+ languages including Basque, Maltese), and memory/session attacks. Protocol-based hexagonal architecture with LangChain integration.
Author-email: Joerg Bollwahn <sookoothaii@proton.me>
Maintainer-email: Joerg Bollwahn <sookoothaii@proton.me>
License: MIT
Project-URL: Homepage, https://github.com/sookoothaii/llm-security-firewall
Project-URL: Repository, https://github.com/sookoothaii/llm-security-firewall
Project-URL: Issues, https://github.com/sookoothaii/llm-security-firewall/issues
Project-URL: Changelog, https://github.com/sookoothaii/llm-security-firewall/blob/main/CHANGELOG.md
Keywords: llm,security,firewall,ai-safety,adversarial-robustness,memory-poisoning,evidence-validation,dempster-shafer,conformal-prediction
Classifier: Development Status :: 4 - Beta
Classifier: Intended Audience :: Developers
Classifier: Intended Audience :: Science/Research
Classifier: License :: OSI Approved :: MIT License
Classifier: Programming Language :: Python :: 3.12
Classifier: Programming Language :: Python :: 3.13
Classifier: Topic :: Security
Classifier: Topic :: Scientific/Engineering :: Artificial Intelligence
Classifier: Topic :: Software Development :: Libraries :: Python Modules
Requires-Python: >=3.12
License-File: LICENSE
Requires-Dist: numpy>=1.24.0
Requires-Dist: scipy>=1.11.0
Requires-Dist: pyyaml>=6.0
Requires-Dist: blake3>=0.3.0
Requires-Dist: requests>=2.31.0
Requires-Dist: pydantic>=2.0.0
Requires-Dist: psutil>=5.9.0
Requires-Dist: cryptography>=41.0.0
Requires-Dist: onnx>=1.14.0
Requires-Dist: onnxruntime>=1.16.0
Requires-Dist: tokenizers>=0.20.0
Provides-Extra: full
Requires-Dist: sentence-transformers>=2.2.0; extra == "full"
Requires-Dist: torch>=2.0.0; extra == "full"
Requires-Dist: transformers>=4.30.0; extra == "full"
Requires-Dist: scikit-learn>=1.3.0; extra == "full"
Provides-Extra: database
Requires-Dist: psycopg[binary]>=3.1.0; extra == "database"
Requires-Dist: redis>=5.0.0; extra == "database"
Provides-Extra: dev
Requires-Dist: pytest>=7.4.0; extra == "dev"
Requires-Dist: pytest-cov>=4.1.0; extra == "dev"
Requires-Dist: ruff>=0.1.0; extra == "dev"
Requires-Dist: mypy>=1.7.0; extra == "dev"
Requires-Dist: types-PyYAML>=6.0.0; extra == "dev"
Requires-Dist: types-requests>=2.31.0; extra == "dev"
Provides-Extra: langchain
Requires-Dist: langchain>=0.0.200; extra == "langchain"
Provides-Extra: monitoring
Requires-Dist: prometheus-client>=0.17.0; extra == "monitoring"
Provides-Extra: personality
Requires-Dist: psycopg3>=3.2.12; extra == "personality"
Requires-Dist: numpy>=1.24.0; extra == "personality"
Provides-Extra: biometrics
Requires-Dist: psycopg3>=3.2.12; extra == "biometrics"
Requires-Dist: scikit-learn>=1.3.0; extra == "biometrics"
Requires-Dist: pandas>=2.0.0; extra == "biometrics"
Requires-Dist: numpy>=1.24.0; extra == "biometrics"
Provides-Extra: care
Requires-Dist: psycopg3>=3.2.12; extra == "care"
Requires-Dist: prometheus-client>=0.17.0; extra == "care"
Requires-Dist: numpy>=1.24.0; extra == "care"
Provides-Extra: full-all
Requires-Dist: llm-security-firewall[biometrics,care,database,full,monitoring,personality]; extra == "full-all"
Dynamic: license-file
